Verilog-124-239/VerilogDM-124-239.v
/*
Verilog Dataflow Modelling 
Title    : Data Encryption using XOR
Reg. No  : 16CO124, 16CO239
Abstract : The project simulates a circuit for encryption of data using Rule 30 of cellular automaton
Functionalities : 1.Encryption of data input by user 
				  2.Decryption of encrypted data	
				  3.Implementation of Rule 30 of cellular automaton
Brief descriptions : The code contains individual modules for shift register, 8x1 multiplexer, XOR circuit and
					 2x1 multiplexer using dataflow modelling
*/

module shift_reg(in, clk, out); //Shift register
	input [7:0]in;				//Input to shift register
	input clk;					//Clock

	output [7:0]out;			//Output from shift register
	reg [7:0]out;
	always@(posedge clk)
		out = in;
endmodule	

module mux8x1(in, out, sel);	//8x1 multiplexer
	input [7:0]in;				//Input line to multiplexer
	input [2:0]sel;				//Select line
	output out;					//Output line from multiplexer
	
	assign out = in[0] &~sel[0] & ~sel[1] & ~sel[2] | //Depending on select line, the corresponding input is selected
				in[1] &  sel[0] & ~sel[1] & ~sel[2] |
				in[2] & ~sel[0] &  sel[1] & ~sel[2] | 
				in[3] &  sel[0] &  sel[1] & ~sel[2] | 
				in[4] & ~sel[0] & ~sel[1] &  sel[2] | 
				in[5] &  sel[0] & ~sel[1] &  sel[2] | 
				in[6] & ~sel[0] &  sel[1] &  sel[2] | 
				in[7] &  sel[0] &  sel[1] &  sel[2] ; 			
endmodule		

module xor1(in,key,out);	//XOR circuit
	input [7:0]in;		//Input to circuit 
	input [7:0]key;		//Key to be XORed
	output [7:0]out;	


	assign out[7]=key[7]^in[7];	//XOR the individual bits
	assign out[6]=key[6]^in[6];
	assign out[5]=key[5]^in[5];
	assign out[4]=key[4]^in[4];
	assign out[3]=key[3]^in[3];
	assign out[2]=key[2]^in[2];
	assign out[1]=key[1]^in[1];
	assign out[0]=key[0]^in[0];

endmodule

module mux2x1(in, sel,out);	//2x1 multiplexer
	input [7:0]in;		//Input line to multiplexer
	input sel;			//Select line 
	output  [7:0]out;	//Output line

	assign out[7]=(sel&0)|(~sel&in[7]); //00011000 is initial key. If select is 1, initial key is selcted.
	assign out[6]=(sel&0)|(~sel&in[6]); //For remaining inputs, select is 0, and feedback key is selected.
	assign out[5]=(sel&0)|(~sel&in[5]);
	assign out[4]=(sel&1)|(~sel&in[4]);
	assign out[3]=(sel&1)|(~sel&in[3]);
	assign out[2]=(sel&0)|(~sel&in[2]);
	assign out[1]=(sel&0)|(~sel&in[1]);
	assign out[0]=(sel&0)|(~sel&in[0]);

endmodule

module VerilogDM_124_239(
	input  [7:0] data,		//Data to be encrypted : user input
	output [7:0] enc_data,	//Encrypted data to be given as output
	input  clk,				//Clock
	input  sel,				//Select line for 2x1 multiplexer
	output [7:0] oldkey,	//Feedback key
	output [7:0] dec_data);	//Decrypted data
	
	reg [7:0] dec_data;
	reg [7:0] enc_data;

	output  [7:0] feedback;  //Feedback key input to shift register 1
	output  [7:0] midkey;	 //Output from shift register 1
	output  [7:0] newkey;	 //Output from 8x1 multiplexer
	wire    [7:0] en_data;	 //Encrypted data	
	wire    [7:0] de_data;	 //Decrypted data	

	parameter [7:0]in = 8'b00011110; //Input to 8x1 multiplexer: Rule 30 of cellular automaton

	mux2x1 m(feedback, sel, oldkey);

	shift_reg s1(oldkey, clk, midkey); //Shift register 1

	mux8x1 m0(in, newkey[0], {midkey[7], midkey[0], midkey[1]});
	mux8x1 m1(in, newkey[1], {midkey[0], midkey[1], midkey[2]});
	mux8x1 m2(in, newkey[2], {midkey[1], midkey[2], midkey[3]});
	mux8x1 m3(in, newkey[3], {midkey[2], midkey[3], midkey[4]});
	mux8x1 m4(in, newkey[4], {midkey[3], midkey[4], midkey[5]});
	mux8x1 m5(in, newkey[5], {midkey[4], midkey[5], midkey[6]});
	mux8x1 m6(in, newkey[6], {midkey[5], midkey[6], midkey[7]});
	mux8x1 m7(in, newkey[7], {midkey[6], midkey[7], midkey[0]});

	shift_reg s2(newkey, ~clk, feedback); //Shift register 2

	xor1 x(data, feedback, en_data); 	//XOR circuit for encryption
	xor1 x1(en_data, oldkey, de_data);  //XOR circuit for decryption

	always @(en_data or data or newkey or de_data or feedback) begin
		enc_data = en_data;
		dec_data = de_data;
	end	
endmodule

Verilog-124-239/Verilog-124-239.v
/*
Verilog Testbench
Title    : Data Encryption using XOR
Reg. No  : 16CO124, 16CO239
Abstract : The project simulates a circuit for encryption of data using Rule 30 of cellular automaton
Functionalities : 1.Encryption of data input by user 
				  2.Decryption of encrypted data	
				  3.Implementation of Rule 30 of cellular automaton
Brief descriptions : The code consists of a testbench to simulate the dataflow and behavioral models of the project.
					 It also generates the gkt wave file. User inputs are given and corresponding encrypted data
*/

module Verilog_124_239;
	reg[7:0] data;		//User input
	wire [7:0] enc_data;//Encrypted data
	wire [7:0]newkey;	//Key used for encryption
	reg clk;			//Clock
	reg sel;			//Select line for 2x1 multiplexer to select between initial and feedback key
	wire [7:0]de_data;	//Decrypted data
	VerilogDM_124_239 m(data, enc_data, clk, sel, newkey, de_data);
	//VerilogBM_124_239 m(data, enc_data, clk, sel, newkey, de_data);
	initial begin
		$dumpfile(" VerilogDM-124-239.vcd");
		//$dumpfile(" VerilogBM-124-239.vcd");
		$dumpvars(0, Verilog_124_239);
		$display("\t\tTime User Input\t Encrypted data\t Key\t\t Decrypted data");
	end
    
	initial begin 
		clk = 0;
		data = 8'b00000000;
		sel = 1;
		#10 sel =0;
		#10 data = 8'b10001010;
		#10 data = 8'b10001011;
		#10 data = 8'b10101000;
		#10 data = 8'b10000110;
		#10 data = 8'b10110000;
		#10 data = 8'b10000111;
		#10 data = 8'b10100111;
		#10 data = 8'b11100101;
		#10 data = 8'b10100111;
		#10 data = 8'b10001010;
		#10 data = 8'b10001011;
		#10 data = 8'b10101000;
		#10 data = 8'b10000110;
		#10 data = 8'b10110000;
		#10 data = 8'b11100111;
		#10 data = 8'b10100111;
		#10 data = 8'b11110101;
		#10 data = 8'b10100111;
		
	end	
	initial $monitor("%t %b\t   %b\t %b\t %b\t",$time, data, enc_data,newkey, de_data);
	always #5 clk = ~clk;
	initial #200 $finish;
endmodule

Verilog-124-239/ VerilogDM-124-239.vcd
$date
	Tue Nov  7 23:21:24 2017
$end
$version
	Icarus Verilog
$end
$timescale
	1s
$end
$scope module Verilog_124_239 $end
$var wire 8 ! newkey [7:0] $end
$var wire 8 " enc_data [7:0] $end
$var wire 8 # de_data [7:0] $end
$var reg 1 $ clk $end
$var reg 8 % data [7:0] $end
$var reg 1 & sel $end
$scope module m $end
$var wire 1 $ clk $end
$var wire 8 ' data [7:0] $end
$var wire 1 & sel $end
$var wire 8 ( oldkey [7:0] $end
$var wire 8 ) newkey [7:0] $end
$var wire 8 * midkey [7:0] $end
$var wire 8 + feedback [7:0] $end
$var wire 8 , en_data [7:0] $end
$var wire 8 - de_data [7:0] $end
$var reg 8 . dec_data [7:0] $end
$var reg 8 / enc_data [7:0] $end
$scope module m $end
$var wire 1 & sel $end
$var wire 8 0 out [7:0] $end
$var wire 8 1 in [7:0] $end
$upscope $end
$scope module m0 $end
$var wire 8 2 in [7:0] $end
$var wire 1 3 out $end
$var wire 3 4 sel [2:0] $end
$upscope $end
$scope module m1 $end
$var wire 8 5 in [7:0] $end
$var wire 1 6 out $end
$var wire 3 7 sel [2:0] $end
$upscope $end
$scope module m2 $end
$var wire 8 8 in [7:0] $end
$var wire 1 9 out $end
$var wire 3 : sel [2:0] $end
$upscope $end
$scope module m3 $end
$var wire 8 ; in [7:0] $end
$var wire 1 < out $end
$var wire 3 = sel [2:0] $end
$upscope $end
$scope module m4 $end
$var wire 8 > in [7:0] $end
$var wire 1 ? out $end
$var wire 3 @ sel [2:0] $end
$upscope $end
$scope module m5 $end
$var wire 8 A in [7:0] $end
$var wire 1 B out $end
$var wire 3 C sel [2:0] $end
$upscope $end
$scope module m6 $end
$var wire 8 D in [7:0] $end
$var wire 1 E out $end
$var wire 3 F sel [2:0] $end
$upscope $end
$scope module m7 $end
$var wire 8 G in [7:0] $end
$var wire 1 H out $end
$var wire 3 I sel [2:0] $end
$upscope $end
$scope module s1 $end
$var wire 1 $ clk $end
$var wire 8 J in [7:0] $end
$var reg 8 K out [7:0] $end
$upscope $end
$scope module s2 $end
$var wire 1 L clk $end
$var wire 8 M in [7:0] $end
$var reg 8 N out [7:0] $end
$upscope $end
$scope module x $end
$var wire 8 O in [7:0] $end
$var wire 8 P key [7:0] $end
$var wire 8 Q out [7:0] $end
$upscope $end
$scope module x1 $end
$var wire 8 R in [7:0] $end
$var wire 8 S key [7:0] $end
$var wire 8 T out [7:0] $end
$upscope $end
$upscope $end
$upscope $end
$enddefinitions $end
#0
$dumpvars
bx T
b11000 S
bx R
bx Q
bx P
b0 O
bx N
bx M
1L
bx K
b11000 J
bx I
xH
b11110 G
bx F
xE
b11110 D
bx C
xB
b11110 A
bx @
x?
b11110 >
bx =
x<
b11110 ;
bx :
x9
b11110 8
bx 7
x6
b11110 5
bx 4
x3
b11110 2
bx 1
b11000 0
bx /
bx .
bx -
bx ,
bx +
bx *
bx )
b11000 (
b0 '
1&
b0 %
0$
bx #
bx "
b11000 !
$end
#5
0H
0E
19
06
03
0?
1B
b101100 )
b101100 M
1<
b0 I
b0 F
b100 C
b110 @
b11 =
b1 :
b0 7
b0 4
0L
b11000 *
b11000 K
1$
#10
b0 #
b0 .
b0 -
b0 T
b101100 "
b101100 /
b101100 ,
b101100 Q
b101100 R
b101100 !
b101100 (
b101100 0
b101100 J
b101100 S
b101100 +
b101100 1
b101100 N
b101100 P
1L
0$
0&
#15
16
0?
0<
1E
b1100110 )
b1100110 M
1B
b100 F
b10 C
b101 @
b110 =
b11 :
b1 7
0L
b101100 *
b101100 K
1$
#20
b1100110 !
b1100110 (
b1100110 0
b1100110 J
b1100110 S
b10001010 #
b10001010 .
b10001010 -
b10001010 T
b11101100 "
b11101100 /
b1100110 +
b1100110 1
b1100110 N
b1100110 P
b11101100 ,
b11101100 Q
b11101100 R
1L
0$
b10001010 %
b10001010 '
b10001010 O
#25
13
1?
0E
1<
09
b10111011 )
b10111011 M
1H
b100 I
b110 F
b11 C
b1 @
b100 =
b110 :
b11 7
b1 4
0L
b1100110 *
b1100110 K
1$
#30
b10111011 !
b10111011 (
b10111011 0
b10111011 J
b10111011 S
b10001011 #
b10001011 .
b10001011 -
b10001011 T
b110000 "
b110000 /
b10111011 +
b10111011 1
b10111011 N
b10111011 P
b110000 ,
b110000 Q
b110000 R
1L
0$
b10001011 %
b10001011 '
b10001011 O
#35
0?
03
0E
0B
09
06
1H
b10001000 )
b10001000 M
1<
b11 I
b101 F
b110 C
b111 @
b11 =
b101 :
b110 7
b111 4
0L
b10111011 *
b10111011 K
1$
#40
b10001000 !
b10001000 (
b10001000 0
b10001000 J
b10001000 S
b10101000 #
b10101000 .
b10101000 -
b10101000 T
b100000 "
b100000 /
b10001000 +
b10001000 1
b10001000 N
b10001000 P
b100000 ,
b100000 Q
b100000 R
1L
0$
b10101000 %
b10101000 '
b10101000 O
#45
1E
19
1H
1?
1<
b11011101 )
b11011101 M
13
b10 I
b1 F
b0 C
b100 @
b10 =
b1 :
b0 7
b100 4
0L
b10001000 *
b10001000 K
1$
#50
b11011101 !
b11011101 (
b11011101 0
b11011101 J
b11011101 S
b10000110 #
b10000110 .
b10000110 -
b10000110 T
b1011011 "
b1011011 /
b11011101 +
b11011101 1
b11011101 N
b11011101 P
b1011011 ,
b1011011 Q
b1011011 R
1L
0$
b10000110 %
b10000110 '
b10000110 O
#55
0H
0<
0?
03
0B
b1000100 )
b1000100 M
06
b111 I
b11 F
b101 C
b110 @
b111 =
b11 :
b101 7
b110 4
0L
b11011101 *
b11011101 K
1$
#60
b1000100 !
b1000100 (
b1000100 0
b1000100 J
b1000100 S
b10110000 #
b10110000 .
b10110000 -
b10110000 T
b11110100 "
b11110100 /
b1000100 +
b1000100 1
b1000100 N
b1000100 P
b11110100 ,
b11110100 Q
b11110100 R
1L
0$
b10110000 %
b10110000 '
b10110000 O
#65
1B
16
1H
1E
1<
b11101110 )
b11101110 M
19
b100 I
b10 F
b1 C
b0 @
b100 =
b10 :
b1 7
b0 4
0L
b1000100 *
b1000100 K
1$
#70
b11101110 !
b11101110 (
b11101110 0
b11101110 J
b11101110 S
b10000111 #
b10000111 .
b10000111 -
b10000111 T
b1101001 "
b1101001 /
b11101110 +
b11101110 1
b11101110 N
b11101110 P
b1101001 ,
b1101001 Q
b1101001 R
1L
0$
b10000111 %
b10000111 '
b10000111 O
#75
0E
09
0H
0<
0?
b100010 )
b100010 M
03
b110 I
b111 F
b11 C
b101 @
b110 =
b111 :
b11 7
b101 4
0L
b11101110 *
b11101110 K
1$
#80
b100010 !
b100010 (
b100010 0
b100010 J
b100010 S
b10100111 #
b10100111 .
b10100111 -
b10100111 T
b10000101 "
b10000101 /
b100010 +
b100010 1
b100010 N
b100010 P
b10000101 ,
b10000101 Q
b10000101 R
1L
0$
b10100111 %
b10100111 '
b10100111 O
#85
1?
13
1E
1B
19
b1110111 )
b1110111 M
16
b0 I
b100 F
b10 C
b1 @
b0 =
b100 :
b10 7
b1 4
0L
b100010 *
b100010 K
1$
#90
b1110111 !
b1110111 (
b1110111 0
b1110111 J
b1110111 S
b11100101 #
b11100101 .
b11100101 -
b11100101 T
b10010010 "
b10010010 /
b1110111 +
b1110111 1
b1110111 N
b1110111 P
b10010010 ,
b10010010 Q
b10010010 R
1L
0$
b11100101 %
b11100101 '
b11100101 O
#95
0B
06
0E
09
0H
b10001 )
b10001 M
0<
b101 I
b110 F
b111 C
b11 @
b101 =
b110 :
b111 7
b11 4
0L
b1110111 *
b1110111 K
1$
#100
b10001 !
b10001 (
b10001 0
b10001 J
b10001 S
b10100111 #
b10100111 .
b10100111 -
b10100111 T
b10110110 "
b10110110 /
b10001 +
b10001 1
b10001 N
b10001 P
b10110110 ,
b10110110 Q
b10110110 R
1L
0$
b10100111 %
b10100111 '
b10100111 O
#105
1H
1<
1B
1?
16
b10111011 )
b10111011 M
13
b1 I
b0 F
b100 C
b10 @
b1 =
b0 :
b100 7
b10 4
0L
b10001 *
b10001 K
1$
#110
b10111011 !
b10111011 (
b10111011 0
b10111011 J
b10111011 S
b10001010 #
b10001010 .
b10001010 -
b10001010 T
b110001 "
b110001 /
b10111011 +
b10111011 1
b10111011 N
b10111011 P
b110001 ,
b110001 Q
b110001 R
1L
0$
b10001010 %
b10001010 '
b10001010 O
#115
0?
03
0B
06
0E
b10001000 )
b10001000 M
09
b11 I
b101 F
b110 C
b111 @
b11 =
b101 :
b110 7
b111 4
0L
b10111011 *
b10111011 K
1$
#120
b10001000 !
b10001000 (
b10001000 0
b10001000 J
b10001000 S
b10001011 #
b10001011 .
b10001011 -
b10001011 T
b11 "
b11 /
b10001000 +
b10001000 1
b10001000 N
b10001000 P
b11 ,
b11 Q
b11 R
1L
0$
b10001011 %
b10001011 '
b10001011 O
#125
1E
19
1H
1?
1<
b11011101 )
b11011101 M
13
b10 I
b1 F
b0 C
b100 @
b10 =
b1 :
b0 7
b100 4
0L
b10001000 *
b10001000 K
1$
#130
b11011101 !
b11011101 (
b11011101 0
b11011101 J
b11011101 S
b10101000 #
b10101000 .
b10101000 -
b10101000 T
b1110101 "
b1110101 /
b11011101 +
b11011101 1
b11011101 N
b11011101 P
b1110101 ,
b1110101 Q
b1110101 R
1L
0$
b10101000 %
b10101000 '
b10101000 O
#135
0H
0<
0?
03
0B
b1000100 )
b1000100 M
06
b111 I
b11 F
b101 C
b110 @
b111 =
b11 :
b101 7
b110 4
0L
b11011101 *
b11011101 K
1$
#140
b1000100 !
b1000100 (
b1000100 0
b1000100 J
b1000100 S
b10000110 #
b10000110 .
b10000110 -
b10000110 T
b11000010 "
b11000010 /
b1000100 +
b1000100 1
b1000100 N
b1000100 P
b11000010 ,
b11000010 Q
b11000010 R
1L
0$
b10000110 %
b10000110 '
b10000110 O
#145
1B
16
1H
1E
1<
b11101110 )
b11101110 M
19
b100 I
b10 F
b1 C
b0 @
b100 =
b10 :
b1 7
b0 4
0L
b1000100 *
b1000100 K
1$
#150
b11101110 !
b11101110 (
b11101110 0
b11101110 J
b11101110 S
b10110000 #
b10110000 .
b10110000 -
b10110000 T
b1011110 "
b1011110 /
b11101110 +
b11101110 1
b11101110 N
b11101110 P
b1011110 ,
b1011110 Q
b1011110 R
1L
0$
b10110000 %
b10110000 '
b10110000 O
#155
0E
09
0H
0<
0?
b100010 )
b100010 M
03
b110 I
b111 F
b11 C
b101 @
b110 =
b111 :
b11 7
b101 4
0L
b11101110 *
b11101110 K
1$
#160
b100010 !
b100010 (
b100010 0
b100010 J
b100010 S
b11100111 #
b11100111 .
b11100111 -
b11100111 T
b11000101 "
b11000101 /
b100010 +
b100010 1
b100010 N
b100010 P
b11000101 ,
b11000101 Q
b11000101 R
1L
0$
b11100111 %
b11100111 '
b11100111 O
#165
1?
13
1E
1B
19
b1110111 )
b1110111 M
16
b0 I
b100 F
b10 C
b1 @
b0 =
b100 :
b10 7
b1 4
0L
b100010 *
b100010 K
1$
#170
b1110111 !
b1110111 (
b1110111 0
b1110111 J
b1110111 S
b10100111 #
b10100111 .
b10100111 -
b10100111 T
b11010000 "
b11010000 /
b1110111 +
b1110111 1
b1110111 N
b1110111 P
b11010000 ,
b11010000 Q
b11010000 R
1L
0$
b10100111 %
b10100111 '
b10100111 O
#175
0B
06
0E
09
0H
b10001 )
b10001 M
0<
b101 I
b110 F
b111 C
b11 @
b101 =
b110 :
b111 7
b11 4
0L
b1110111 *
b1110111 K
1$
#180
b10001 !
b10001 (
b10001 0
b10001 J
b10001 S
b11110101 #
b11110101 .
b11110101 -
b11110101 T
b11100100 "
b11100100 /
b10001 +
b10001 1
b10001 N
b10001 P
b11100100 ,
b11100100 Q
b11100100 R
1L
0$
b11110101 %
b11110101 '
b11110101 O
#185
1H
1<
1B
1?
16
b10111011 )
b10111011 M
13
b1 I
b0 F
b100 C
b10 @
b1 =
b0 :
b100 7
b10 4
0L
b10001 *
b10001 K
1$
#190
b10111011 !
b10111011 (
b10111011 0
b10111011 J
b10111011 S
b10100111 #
b10100111 .
b10100111 -
b10100111 T
b11100 "
b11100 /
b10111011 +
b10111011 1
b10111011 N
b10111011 P
b11100 ,
b11100 Q
b11100 R
1L
0$
b10100111 %
b10100111 '
b10100111 O
#195
0?
03
0B
06
0E
b10001000 )
b10001000 M
09
b11 I
b101 F
b110 C
b111 @
b11 =
b101 :
b110 7
b111 4
0L
b10111011 *
b10111011 K
1$
#200
b10100111 #
b10100111 .
b10100111 -
b10100111 T
b101111 "
b101111 /
b10001000 !
b10001000 (
b10001000 0
b10001000 J
b10001000 S
b101111 ,
b101111 Q
b101111 R
b10001000 +
b10001000 1
b10001000 N
b10001000 P
1L
0$
